README.rst
setup.py
common_logger/__init__.py
common_logger/base_trace_log.py
common_logger/common_dltags.py
common_logger/wrapper_hook.py
common_logger/wrapper_hook_requests.py
common_logger/zone_flask_interceptors.py
common_logger.egg-info/PKG-INFO
common_logger.egg-info/SOURCES.txt
common_logger.egg-info/dependency_links.txt
common_logger.egg-info/requires.txt
common_logger.egg-info/top_level.txt
common_logger.egg-info/zip-safe
common_logger/model/__init__.py
common_logger/model/normal_log_content.py
common_logger/model/trace_content.py
common_logger/util/__init__.py
common_logger/util/at_fork.py
common_logger/util/find_all_ip.py
common_logger/util/id_creator.py
common_logger/util/log_format.py
common_logger/util/log_rotate_handler.py
common_logger/util/thread_local_util.py